sso_miante/__init__.py
sso_miante/admin.py
sso_miante/apps.py
sso_miante/models.py
sso_miante/tests.py
sso_miante/urls.py
sso_miante/views.py
sso_miante/migrations/0001_initial.py
sso_miante/migrations/0002_ssomiante_server.py
sso_miante/migrations/__init__.py
sso_miante/migrations/__pycache__/0001_initial.cpython-313.pyc
sso_miante/migrations/__pycache__/0002_ssomiante_server.cpython-313.pyc
sso_miante/migrations/__pycache__/__init__.cpython-313.pyc
sso_miante/templates/sso/admin.html
sso_miante/templates/sso/detail.html
sso_miante-1.0.0.dist-info/licenses/LICENSE
sso_miante_client/__init__.py
sso_miante_client/admin.py
sso_miante_client/apps.py
sso_miante_client/models.py
sso_miante_client/tests.py
sso_miante_client/urls.py
sso_miante_client/views.py
sso_miante_client/migrations/__init__.py
sso_miante_client/migrations/__pycache__/__init__.cpython-313.pyc
sso_miante_client/templates/sso-miante/login.html
sso_miante-1.0.0.dist-info/METADATA
sso_miante-1.0.0.dist-info/WHEEL
sso_miante-1.0.0.dist-info/top_level.txt
sso_miante-1.0.0.dist-info/RECORD
